jack_midi_keyboard/__init__.py
jack_midi_keyboard/__main__.py
jack_midi_keyboard-1.0.3.dist-info/LICENSE
jack_midi_keyboard-1.0.3.dist-info/WHEEL
jack_midi_keyboard-1.0.3.dist-info/METADATA
jack_midi_keyboard-1.0.3.dist-info/RECORD
