Metadata-Version: 2.1
Name: jack_midi_keyboard
Version: 1.0.3
Summary: Provides a comfy interface to MIDI keyboards via JACK.
Author-email: Leon Dionne <ldionne@dridesign.sh.cn>
Classifier: License :: OSI Approved :: GNU General Public License v3 or later (GPLv3+)
Requires-Dist: JACK-Client
Project-URL: Home, https://github.com/Zen-Master-SoSo/jack_midi_keyboard
